{
  "name": "Chick Peas With Spinach And Salt Cod",
  "source": "Spain on a Plate, pg.72",
  "author": "Maria Jose Sevilla",
  "course": "mains",
  "country": "Spain",
  "servings": "4",
  "prepTime": "36 hours",
  "cookingTime": "3 hours",
  "slug": "chick-peas-with-spinach-and-salt-cod",
  "dateAdded": "2024-02-16",
  "image": "/recipe-images/chick-peas-with-spinach-and-salt-cod.webp",
  "ingredients": "<ul><li><p>200g dried salt cod</p></li><li><p>300g chick peas</p></li><li><p>2 ltr water</p></li><li><p>1 tsp salt</p></li><li><p>2 onions</p></li><li><p>1 carrot, chopped</p></li><li><p>1/2 bay leaf</p></li><li><p>400g spinach, stalks removed</p></li><li><p>100ml olive oil</p></li></ul>",
  "instructions": "<ul><li><p>Soak the cod in water for 24 to 36 hours, depending on the thickness of the pieces, changing the water at least 3 times.</p></li><li><p>Soak the chickpeas overnight in cold water. </p><p></p></li><li><p> Drain and flake the fish.</p></li><li><p>Drain and rinse the chickpeas.</p><p></p></li><li><p>Slive 1 onion. Place the water, salt, sliced onion, carrot and bay leaf in a large pan and bring to a boil.</p></li><li><p>As soon as the water begins to boil, add the chick peas.</p></li><li><p>Bring back to the boil, cover and simmer gently for 2 to 3 hours until the beans are cooked, adding a little extra water if necessary.</p><p></p></li><li><p>Meanwhile, cook the spinach in a very little salted water for 3 minutes, then drain and chop.</p></li><li><p>Chop the remaining onion, heat the oil and fry the onion until golden.</p></li><li><p>Add the cod and cook, stirring continuously for 1 to 2 minutes.</p><p></p></li><li><p>When the peas are cooked, remove the bay leaf, add the cod and onion mixture and the spinach, boil for 2 minutes.</p></li><li><p>If you like a thicker soup, you can puree some of the chick peas then return them to the soup before serving.</p></li></ul>"
}
